AUTHORS
LICENSE
MANIFEST.in
setup.py
django_photoprocessor.egg-info/PKG-INFO
django_photoprocessor.egg-info/SOURCES.txt
django_photoprocessor.egg-info/dependency_links.txt
django_photoprocessor.egg-info/top_level.txt
photoprocessor/__init__.py
photoprocessor/fields.py
photoprocessor/lib.py
photoprocessor/models.py
photoprocessor/processors.py
photoprocessor/settings.py
photoprocessor/utils.py
photoprocessor/management/__init__.py
photoprocessor/management/commands/__init__.py
photoprocessor/management/commands/reprocess_photos.py
photoprocessor/tests/__init__.py
photoprocessor/tests/common.py
photoprocessor/tests/processors.py