Metadata-Version: 1.0
Name: django-photoprocessor
Version: 0.1.8
Summary: Automated image processing for Django.
Home-page: http://github.com/cuker/django-photoprocessor/
Author: Jason Kraus
Author-email: jasonk@cukerinteractive.com
License: BSD
Platform: UNKNOWN
Classifier: Development Status :: 3 - Alpha
Classifier: Environment :: Web Environment
Classifier: Framework :: Django
Classifier: Intended Audience :: Developers
Classifier: License :: OSI Approved :: BSD License
Classifier: Operating System :: OS Independent
Classifier: Programming Language :: Python :: 2.5
Classifier: Programming Language :: Python :: 2.6
Classifier: Programming Language :: Python :: 2.7
Classifier: Topic :: Utilities
